ragents.py
prepagentest-3.3.0.dist-info/LICENSE.txt
prepagentest-3.3.0.dist-info/METADATA
prepagentest-3.3.0.dist-info/WHEEL
prepagentest-3.3.0.dist-info/top_level.txt
prepagentest-3.3.0.dist-info/RECORD
