Metadata-Version: 2.1
Name: prepagentest
Version: 3.3.0
Summary: some package
Classifier: Programming Language :: Python :: 3
Classifier: License :: OSI Approved :: MIT License
Classifier: Operating System :: OS Independent
License-File: LICENSE.txt
Requires-Dist: pandas
Requires-Dist: numpy
Requires-Dist: datetime
Requires-Dist: tqdm
Requires-Dist: helperagent (==4.0.0)
Requires-Dist: scikit-learn (==1.0.0)
Provides-Extra: dev
Requires-Dist: pytest ; extra == 'dev'
